edc_appointment_app/__init__.py
edc_appointment_app/apps.py
edc_appointment_app/consents.py
edc_appointment_app/forms.py
edc_appointment_app/models.py
edc_appointment_app/sites.py
edc_appointment_app/tests/__init__.py
edc_appointment_app/tests/appointment_app_test_case_mixin.py
edc_appointment_app/visit_schedule/__init__.py
edc_appointment_app/visit_schedule/crfs.py
edc_appointment_app/visit_schedule/visit_schedule1.py
edc_appointment_app/visit_schedule/visit_schedule2.py
edc_appointment_app/visit_schedule/visit_schedule3.py
edc_appointment_app/visit_schedule/visit_schedule4.py
edc_appointment_app/visit_schedule/visit_schedule5.py
edc_appointment_app/visit_schedule/visit_schedule6.py
edc_appointment_app-1.0.0.dist-info/licenses/LICENSE
edc_appointment_app-1.0.0.dist-info/WHEEL
edc_appointment_app-1.0.0.dist-info/METADATA
edc_appointment_app-1.0.0.dist-info/RECORD
